coininfo_elnara/__init__.py
coininfo_elnara/info.py
tests/__init__.py
tests/test_project.py
coininfo_elnara-0.2.1.dist-info/METADATA
coininfo_elnara-0.2.1.dist-info/WHEEL
coininfo_elnara-0.2.1.dist-info/top_level.txt
coininfo_elnara-0.2.1.dist-info/RECORD
