Metadata-Version: 2.1
Name: coininfo-elnara
Version: 0.2.1
Requires-Dist: requests ==2.31.0
